<?xml version="1.0" encoding="UTF-8"?>
<Report xmlns="http://xml.kishou.go.jp/jmaxml1/" xmlns:jmx="http://xml.kishou.go.jp/jmaxml1/">
<Control>
<Title>降灰予報（定時）</Title>
<DateTime>2025-12-28T02:00:00Z</DateTime>
<Status>通常</Status>
<EditorialOffice>気象庁本庁</EditorialOffice>
<PublishingOffice>気象庁</PublishingOffice>
</Control>
<Head xmlns="http://xml.kishou.go.jp/jmaxml1/informationBasis1/">
<Title>火山名　岩手山　降灰予報（定時）</Title>
<ReportDateTime>2025-12-28T11:00:00+09:00</ReportDateTime>
<TargetDateTime>2025-12-28T12:00:00+09:00</TargetDateTime>
<ValidDateTime>2025-12-29T06:00:00+09:00</ValidDateTime>
<EventID>207</EventID>
<InfoType>発表</InfoType>
<Serial>1</Serial>
<InfoKind>降灰予報</InfoKind>
<InfoKindVersion>1.1_0</InfoKindVersion>
<Headline>
<Text>　現在、岩手山は噴火警戒レベル２（火口周辺規制）です。岩手山で噴火が発生した場合には、２８日２１時から２４時までは火口から東方向に降灰が予想されます。</Text>
<Information type="降灰予報（対象火山）">
<Item>
<Kind>
<Name>降灰予報（定時）</Name>
<Code>06</Code>
</Kind>
<Areas codeType="火山名">
<Area>
<Name>岩手山</Name>
<Code>207</Code>
</Area>
</Areas>
</Item>
</Information>
<Information type="降灰予報（対象市町村等）">
<Item>
<Kind>
<Name>降灰</Name>
<Code>70</Code>
</Kind>
<Areas codeType="気象・地震・火山情報／市町村等">
<Area>
<Name>岩手県盛岡市</Name>
<Code>0320100</Code>
</Area>
<Area>
<Name>岩手県宮古市</Name>
<Code>0320200</Code>
</Area>
<Area>
<Name>岩手県二戸市</Name>
<Code>0321300</Code>
</Area>
<Area>
<Name>岩手県八幡平市</Name>
<Code>0321400</Code>
</Area>
<Area>
<Name>岩手県滝沢市</Name>
<Code>0321600</Code>
</Area>
<Area>
<Name>岩手県雫石町</Name>
<Code>0330100</Code>
</Area>
<Area>
<Name>岩手県葛巻町</Name>
<Code>0330200</Code>
</Area>
<Area>
<Name>岩手県岩手町</Name>
<Code>0330300</Code>
</Area>
<Area>
<Name>岩手県岩泉町</Name>
<Code>0348300</Code>
</Area>
<Area>
<Name>岩手県九戸村</Name>
<Code>0350600</Code>
</Area>
<Area>
<Name>岩手県一戸町</Name>
<Code>0352400</Code>
</Area>
</Areas>
</Item>
<Item>
<Kind>
<Name>小さな噴石の落下</Name>
<Code>75</Code>
</Kind>
<Areas codeType="気象・地震・火山情報／市町村等">
<Area>
<Name>岩手県八幡平市</Name>
<Code>0321400</Code>
</Area>
<Area>
<Name>岩手県滝沢市</Name>
<Code>0321600</Code>
</Area>
<Area>
<Name>岩手県雫石町</Name>
<Code>0330100</Code>
</Area>
</Areas>
</Item>
</Information>
</Headline>
</Head>
<Body xmlns="http://xml.kishou.go.jp/jmaxml1/body/volcanology1/" xmlns:jmx_eb="http://xml.kishou.go.jp/jmaxml1/elementBasis1/">
<VolcanoInfo type="降灰予報（対象火山）">
<Item>
<Kind>
<Name>降灰予報（定時）</Name>
<Code>06</Code>
</Kind>
<Areas codeType="火山名">
<Area>
<Name>岩手山</Name>
<Code>207</Code>
<Coordinate description="北緯３９度５１．１５分　東経１４１度００．０７分　標高２０３８ｍ">+3951.15+14100.07+2038/</Coordinate>
</Area>
</Areas>
</Item>
</VolcanoInfo>
<VolcanoInfo type="降灰予報（対象市町村等）">
<Item>
<Kind>
<Name>降灰</Name>
<Code>70</Code>
</Kind>
<Areas codeType="気象・地震・火山情報／市町村等">
<Area>
<Name>岩手県盛岡市</Name>
<Code>0320100</Code>
</Area>
<Area>
<Name>岩手県宮古市</Name>
<Code>0320200</Code>
</Area>
<Area>
<Name>岩手県二戸市</Name>
<Code>0321300</Code>
</Area>
<Area>
<Name>岩手県八幡平市</Name>
<Code>0321400</Code>
</Area>
<Area>
<Name>岩手県滝沢市</Name>
<Code>0321600</Code>
</Area>
<Area>
<Name>岩手県雫石町</Name>
<Code>0330100</Code>
</Area>
<Area>
<Name>岩手県葛巻町</Name>
<Code>0330200</Code>
</Area>
<Area>
<Name>岩手県岩手町</Name>
<Code>0330300</Code>
</Area>
<Area>
<Name>岩手県岩泉町</Name>
<Code>0348300</Code>
</Area>
<Area>
<Name>岩手県九戸村</Name>
<Code>0350600</Code>
</Area>
<Area>
<Name>岩手県一戸町</Name>
<Code>0352400</Code>
</Area>
</Areas>
</Item>
<Item>
<Kind>
<Name>小さな噴石の落下</Name>
<Code>75</Code>
</Kind>
<Areas codeType="気象・地震・火山情報／市町村等">
<Area>
<Name>岩手県八幡平市</Name>
<Code>0321400</Code>
</Area>
<Area>
<Name>岩手県滝沢市</Name>
<Code>0321600</Code>
</Area>
<Area>
<Name>岩手県雫石町</Name>
<Code>0330100</Code>
</Area>
</Areas>
</Item>
</VolcanoInfo>
<AshInfos type="降灰予報（定時）">
<AshInfo type="予報　３時間後">
<StartTime>2025-12-28T12:00:00+09:00</StartTime>
<EndTime>2025-12-28T15:00:00+09:00</EndTime>
<Item>
<Kind>
<Name>降灰</Name>
<Code>70</Code>
<Property>
<jmx_eb:Polygon type="位置（度）">+39.8745+140.9600/+39.8799+140.9800/+39.8799+141.0000/+39.8799+141.0200/+39.8796+141.0400/+39.8781+141.0600/+39.8682+141.0800/+39.8600+141.0910/+39.8598+141.1000/+39.8596+141.1200/+39.8592+141.1400/+39.8585+141.1600/+39.8572+141.1800/+39.8549+141.2000/+39.8514+141.2200/+39.8478+141.2400/+39.8400+141.2534/+39.8394+141.2600/+39.8380+141.2800/+39.8370+141.3000/+39.8350+141.3200/+39.8363+141.3400/+39.8348+141.3600/+39.8333+141.3800/+39.8311+141.4000/+39.8280+141.4200/+39.8285+141.4400/+39.8258+141.4600/+39.8205+141.4800/+39.8200+141.4824/+39.8154+141.5000/+39.8070+141.5200/+39.8000+141.5389/+39.7997+141.5400/+39.7970+141.5600/+39.7924+141.5800/+39.7891+141.6000/+39.7833+141.6200/+39.7800+141.6303/+39.7767+141.6400/+39.7702+141.6600/+39.7633+141.6800/+39.7600+141.6875/+39.7486+141.7000/+39.7400+141.7150/+39.7362+141.7200/+39.7288+141.7400/+39.7221+141.7600/+39.7200+141.7642/+39.7122+141.7800/+39.7022+141.8000/+39.7000+141.8031/+39.6961+141.8000/+39.6858+141.7800/+39.6808+141.7600/+39.6811+141.7400/+39.6854+141.7200/+39.6900+141.7000/+39.6963+141.6800/+39.7000+141.6705/+39.7056+141.6600/+39.7100+141.6400/+39.7119+141.6200/+39.7129+141.6000/+39.7147+141.5800/+39.7166+141.5600/+39.7181+141.5400/+39.7200+141.5376/+39.7287+141.5200/+39.7302+141.5000/+39.7319+141.4800/+39.7320+141.4600/+39.7322+141.4400/+39.7322+141.4200/+39.7400+141.4090/+39.7437+141.4000/+39.7444+141.3800/+39.7456+141.3600/+39.7465+141.3400/+39.7473+141.3200/+39.7600+141.3046/+39.7621+141.3000/+39.7633+141.2800/+39.7650+141.2600/+39.7702+141.2400/+39.7800+141.2232/+39.7802+141.2200/+39.7810+141.2000/+39.7824+141.1800/+39.7847+141.1600/+39.7921+141.1400/+39.8000+141.1279/+39.8002+141.1200/+39.8004+141.1000/+39.8006+141.0800/+39.8009+141.0600/+39.8047+141.0400/+39.8200+141.0239/+39.8200+141.0200/+39.8200+141.0000/+39.8201+140.9800/+39.8259+140.9600/+39.8400+140.9459/+39.8600+140.9455/+39.8745+140.9600/</jmx_eb:Polygon>
<jmx_eb:PlumeDirection type="降灰の方向" unit="漢字" description="東">東</jmx_eb:PlumeDirection>
<Distance type="降灰の到達距離" unit="km">70</Distance>
</Property>
</Kind>
<Areas codeType="気象・地震・火山情報／市町村等">
<Area>
<Name>岩手県盛岡市</Name>
<Code>0320100</Code>
</Area>
<Area>
<Name>岩手県宮古市</Name>
<Code>0320200</Code>
</Area>
<Area>
<Name>岩手県八幡平市</Name>
<Code>0321400</Code>
</Area>
<Area>
<Name>岩手県滝沢市</Name>
<Code>0321600</Code>
</Area>
<Area>
<Name>岩手県雫石町</Name>
<Code>0330100</Code>
</Area>
<Area>
<Name>岩手県岩泉町</Name>
<Code>0348300</Code>
</Area>
</Areas>
</Item>
<Item>
<Kind>
<Name>小さな噴石の落下</Name>
<Code>75</Code>
<Property>
<Size type="小さな噴石の大きさ" unit="cm">1</Size>
<jmx_eb:Polygon type="位置（度）">+39.8788+140.9800/+39.8600+140.9991/+39.8570+141.0000/+39.8473+141.0200/+39.8400+141.0342/+39.8327+141.0200/+39.8238+141.0000/+39.8212+140.9800/+39.8400+140.9612/+39.8600+140.9612/+39.8788+140.9800/</jmx_eb:Polygon>
<jmx_eb:PlumeDirection type="小さな噴石の落下方向" unit="漢字" description="東">東</jmx_eb:PlumeDirection>
<Distance type="小さな噴石の到達距離" unit="km">4</Distance>
</Property>
</Kind>
<Areas codeType="気象・地震・火山情報／市町村等">
<Area>
<Name>岩手県八幡平市</Name>
<Code>0321400</Code>
</Area>
<Area>
<Name>岩手県滝沢市</Name>
<Code>0321600</Code>
</Area>
<Area>
<Name>岩手県雫石町</Name>
<Code>0330100</Code>
</Area>
</Areas>
</Item>
</AshInfo>
<AshInfo type="予報　６時間後">
<StartTime>2025-12-28T15:00:00+09:00</StartTime>
<EndTime>2025-12-28T18:00:00+09:00</EndTime>
<Item>
<Kind>
<Name>降灰</Name>
<Code>70</Code>
<Property>
<jmx_eb:Polygon type="位置（度）">+39.8728+140.9600/+39.8799+140.9800/+39.8799+141.0000/+39.8799+141.0200/+39.8797+141.0400/+39.8794+141.0600/+39.8786+141.0800/+39.8776+141.1000/+39.8771+141.1200/+39.8764+141.1400/+39.8751+141.1600/+39.8728+141.1800/+39.8717+141.2000/+39.8641+141.2200/+39.8600+141.2346/+39.8599+141.2400/+39.8588+141.2600/+39.8584+141.2800/+39.8579+141.3000/+39.8572+141.3200/+39.8600+141.3317/+39.8665+141.3400/+39.8635+141.3600/+39.8616+141.3800/+39.8600+141.3896/+39.8589+141.4000/+39.8561+141.4200/+39.8514+141.4400/+39.8530+141.4600/+39.8430+141.4800/+39.8400+141.4855/+39.8358+141.5000/+39.8299+141.5200/+39.8280+141.5400/+39.8268+141.5600/+39.8226+141.5800/+39.8200+141.5902/+39.8172+141.6000/+39.8138+141.6200/+39.8099+141.6400/+39.8045+141.6600/+39.8000+141.6719/+39.7846+141.6800/+39.7800+141.6861/+39.7751+141.7000/+39.7728+141.7200/+39.7712+141.7400/+39.7661+141.7600/+39.7600+141.7736/+39.7400+141.7718/+39.7368+141.7600/+39.7357+141.7400/+39.7377+141.7200/+39.7395+141.7000/+39.7400+141.6971/+39.7475+141.6800/+39.7531+141.6600/+39.7560+141.6400/+39.7574+141.6200/+39.7586+141.6000/+39.7600+141.5897/+39.7610+141.5800/+39.7623+141.5600/+39.7637+141.5400/+39.7667+141.5200/+39.7673+141.5000/+39.7677+141.4800/+39.7679+141.4600/+39.7680+141.4400/+39.7760+141.4200/+39.7800+141.4076/+39.7805+141.4000/+39.7822+141.3800/+39.7828+141.3600/+39.7830+141.3400/+39.7829+141.3200/+39.7871+141.3000/+39.7883+141.2800/+39.7883+141.2600/+39.7971+141.2400/+39.8000+141.2346/+39.8006+141.2200/+39.8008+141.2000/+39.8016+141.1800/+39.8018+141.1600/+39.8018+141.1400/+39.8016+141.1200/+39.8018+141.1000/+39.8032+141.0800/+39.8060+141.0600/+39.8200+141.0435/+39.8200+141.0400/+39.8200+141.0200/+39.8200+141.0000/+39.8201+140.9800/+39.8278+140.9600/+39.8400+140.9478/+39.8600+140.9472/+39.8728+140.9600/</jmx_eb:Polygon>
<jmx_eb:PlumeDirection type="降灰の方向" unit="漢字" description="東">東</jmx_eb:PlumeDirection>
<Distance type="降灰の到達距離" unit="km">70</Distance>
</Property>
</Kind>
<Areas codeType="気象・地震・火山情報／市町村等">
<Area>
<Name>岩手県盛岡市</Name>
<Code>0320100</Code>
</Area>
<Area>
<Name>岩手県宮古市</Name>
<Code>0320200</Code>
</Area>
<Area>
<Name>岩手県八幡平市</Name>
<Code>0321400</Code>
</Area>
<Area>
<Name>岩手県滝沢市</Name>
<Code>0321600</Code>
</Area>
<Area>
<Name>岩手県雫石町</Name>
<Code>0330100</Code>
</Area>
<Area>
<Name>岩手県岩手町</Name>
<Code>0330300</Code>
</Area>
<Area>
<Name>岩手県岩泉町</Name>
<Code>0348300</Code>
</Area>
</Areas>
</Item>
<Item>
<Kind>
<Name>小さな噴石の落下</Name>
<Code>75</Code>
<Property>
<Size type="小さな噴石の大きさ" unit="cm">1</Size>
<jmx_eb:Polygon type="位置（度）">+39.8788+140.9800/+39.8747+141.0000/+39.8600+141.0149/+39.8424+141.0200/+39.8400+141.0246/+39.8377+141.0200/+39.8244+141.0000/+39.8212+140.9800/+39.8400+140.9612/+39.8600+140.9612/+39.8788+140.9800/</jmx_eb:Polygon>
<jmx_eb:PlumeDirection type="小さな噴石の落下方向" unit="漢字" description="東">東</jmx_eb:PlumeDirection>
<Distance type="小さな噴石の到達距離" unit="km">4</Distance>
</Property>
</Kind>
<Areas codeType="気象・地震・火山情報／市町村等">
<Area>
<Name>岩手県八幡平市</Name>
<Code>0321400</Code>
</Area>
<Area>
<Name>岩手県滝沢市</Name>
<Code>0321600</Code>
</Area>
<Area>
<Name>岩手県雫石町</Name>
<Code>0330100</Code>
</Area>
</Areas>
</Item>
</AshInfo>
<AshInfo type="予報　９時間後">
<StartTime>2025-12-28T18:00:00+09:00</StartTime>
<EndTime>2025-12-28T21:00:00+09:00</EndTime>
<Item>
<Kind>
<Name>降灰</Name>
<Code>70</Code>
<Property>
<jmx_eb:Polygon type="位置（度）">+39.9068+141.1200/+39.9058+141.1400/+39.9066+141.1600/+39.9078+141.1800/+39.9046+141.2000/+39.9000+141.2128/+39.8995+141.2200/+39.8980+141.2400/+39.8966+141.2600/+39.8958+141.2800/+39.8904+141.3000/+39.8924+141.3200/+39.8937+141.3400/+39.8924+141.3600/+39.8908+141.3800/+39.8881+141.4000/+39.8845+141.4200/+39.8800+141.4325/+39.8779+141.4400/+39.8743+141.4600/+39.8702+141.4800/+39.8671+141.5000/+39.8631+141.5200/+39.8600+141.5336/+39.8583+141.5400/+39.8441+141.5600/+39.8400+141.5665/+39.8289+141.5800/+39.8200+141.5931/+39.8158+141.6000/+39.8174+141.6200/+39.8189+141.6400/+39.8167+141.6600/+39.8110+141.6800/+39.8058+141.7000/+39.8007+141.7200/+39.8000+141.7227/+39.7990+141.7200/+39.7937+141.7000/+39.7903+141.6800/+39.7878+141.6600/+39.7875+141.6400/+39.7889+141.6200/+39.7904+141.6000/+39.7866+141.5800/+39.7838+141.5600/+39.7845+141.5400/+39.7847+141.5200/+39.7854+141.5000/+39.7861+141.4800/+39.7886+141.4600/+39.7917+141.4400/+39.7945+141.4200/+39.7961+141.4000/+39.7995+141.3800/+39.8000+141.3767/+39.8013+141.3600/+39.8012+141.3400/+39.8000+141.3227/+39.7996+141.3200/+39.8000+141.3196/+39.8066+141.3000/+39.8071+141.2800/+39.8078+141.2600/+39.8096+141.2400/+39.8130+141.2200/+39.8190+141.2000/+39.8200+141.1977/+39.8207+141.1800/+39.8207+141.1600/+39.8205+141.1400/+39.8203+141.1200/+39.8203+141.1000/+39.8202+141.0800/+39.8201+141.0600/+39.8201+141.0400/+39.8201+141.0200/+39.8200+141.0000/+39.8201+140.9800/+39.8322+140.9600/+39.8400+140.9522/+39.8600+140.9509/+39.8690+140.9600/+39.8799+140.9800/+39.8800+141.0000/+39.8799+141.0200/+39.8799+141.0400/+39.8800+141.0489/+39.8896+141.0600/+39.8961+141.0800/+39.8992+141.1000/+39.9000+141.1080/+39.9068+141.1200/</jmx_eb:Polygon>
<jmx_eb:PlumeDirection type="降灰の方向" unit="漢字" description="東">東</jmx_eb:PlumeDirection>
<Distance type="降灰の到達距離" unit="km">60</Distance>
</Property>
</Kind>
<Areas codeType="気象・地震・火山情報／市町村等">
<Area>
<Name>岩手県盛岡市</Name>
<Code>0320100</Code>
</Area>
<Area>
<Name>岩手県八幡平市</Name>
<Code>0321400</Code>
</Area>
<Area>
<Name>岩手県滝沢市</Name>
<Code>0321600</Code>
</Area>
<Area>
<Name>岩手県雫石町</Name>
<Code>0330100</Code>
</Area>
<Area>
<Name>岩手県葛巻町</Name>
<Code>0330200</Code>
</Area>
<Area>
<Name>岩手県岩手町</Name>
<Code>0330300</Code>
</Area>
<Area>
<Name>岩手県岩泉町</Name>
<Code>0348300</Code>
</Area>
</Areas>
</Item>
<Item>
<Kind>
<Name>小さな噴石の落下</Name>
<Code>75</Code>
<Property>
<Size type="小さな噴石の大きさ" unit="cm">1</Size>
<jmx_eb:Polygon type="位置（度）">+39.8788+140.9800/+39.8736+141.0000/+39.8600+141.0184/+39.8422+141.0200/+39.8400+141.0209/+39.8395+141.0200/+39.8250+141.0000/+39.8212+140.9800/+39.8400+140.9612/+39.8600+140.9612/+39.8788+140.9800/</jmx_eb:Polygon>
<jmx_eb:PlumeDirection type="小さな噴石の落下方向" unit="漢字" description="東">東</jmx_eb:PlumeDirection>
<Distance type="小さな噴石の到達距離" unit="km">4</Distance>
</Property>
</Kind>
<Areas codeType="気象・地震・火山情報／市町村等">
<Area>
<Name>岩手県八幡平市</Name>
<Code>0321400</Code>
</Area>
<Area>
<Name>岩手県滝沢市</Name>
<Code>0321600</Code>
</Area>
<Area>
<Name>岩手県雫石町</Name>
<Code>0330100</Code>
</Area>
</Areas>
</Item>
</AshInfo>
<AshInfo type="予報　１２時間後">
<StartTime>2025-12-28T21:00:00+09:00</StartTime>
<EndTime>2025-12-29T00:00:00+09:00</EndTime>
<Item>
<Kind>
<Name>降灰</Name>
<Code>70</Code>
<Property>
<jmx_eb:Polygon type="位置（度）">+39.9665+141.1200/+39.9748+141.1400/+39.9753+141.1600/+39.9791+141.1800/+39.9758+141.2000/+39.9716+141.2200/+39.9684+141.2400/+39.9663+141.2600/+39.9600+141.2740/+39.9587+141.2800/+39.9577+141.3000/+39.9558+141.3200/+39.9515+141.3400/+39.9474+141.3600/+39.9443+141.3800/+39.9400+141.3933/+39.9380+141.4000/+39.9334+141.4200/+39.9337+141.4400/+39.9260+141.4600/+39.9200+141.4710/+39.9165+141.4800/+39.9099+141.5000/+39.9000+141.5195/+39.8997+141.5200/+39.8917+141.5400/+39.8800+141.5539/+39.8686+141.5600/+39.8631+141.5800/+39.8600+141.5907/+39.8540+141.5800/+39.8444+141.5600/+39.8400+141.5583/+39.8315+141.5400/+39.8281+141.5200/+39.8251+141.5000/+39.8228+141.4800/+39.8226+141.4600/+39.8224+141.4400/+39.8306+141.4200/+39.8355+141.4000/+39.8400+141.3830/+39.8403+141.3800/+39.8403+141.3600/+39.8400+141.3520/+39.8386+141.3400/+39.8400+141.3345/+39.8409+141.3200/+39.8400+141.3009/+39.8399+141.3000/+39.8400+141.2996/+39.8419+141.2800/+39.8453+141.2600/+39.8459+141.2400/+39.8489+141.2200/+39.8535+141.2000/+39.8535+141.1800/+39.8509+141.1600/+39.8470+141.1400/+39.8429+141.1200/+39.8415+141.1000/+39.8400+141.0867/+39.8340+141.0800/+39.8221+141.0600/+39.8207+141.0400/+39.8202+141.0200/+39.8201+141.0000/+39.8201+140.9800/+39.8275+140.9600/+39.8400+140.9475/+39.8600+140.9456/+39.8744+140.9600/+39.8799+140.9800/+39.8800+140.9812/+39.8986+141.0000/+39.8997+141.0200/+39.9000+141.0232/+39.9159+141.0400/+39.9200+141.0490/+39.9313+141.0600/+39.9400+141.0756/+39.9443+141.0800/+39.9575+141.1000/+39.9600+141.1099/+39.9665+141.1200/</jmx_eb:Polygon>
<jmx_eb:Polygon type="位置（度）">+39.8620+141.6400/+39.8618+141.6600/+39.8600+141.6778/+39.8537+141.6600/+39.8544+141.6400/+39.8600+141.6218/+39.8620+141.6400/</jmx_eb:Polygon>
<jmx_eb:PlumeDirection type="降灰の方向" unit="漢字" description="東">東</jmx_eb:PlumeDirection>
<Distance type="降灰の到達距離" unit="km">60</Distance>
</Property>
</Kind>
<Areas codeType="気象・地震・火山情報／市町村等">
<Area>
<Name>岩手県盛岡市</Name>
<Code>0320100</Code>
</Area>
<Area>
<Name>岩手県八幡平市</Name>
<Code>0321400</Code>
</Area>
<Area>
<Name>岩手県滝沢市</Name>
<Code>0321600</Code>
</Area>
<Area>
<Name>岩手県雫石町</Name>
<Code>0330100</Code>
</Area>
<Area>
<Name>岩手県葛巻町</Name>
<Code>0330200</Code>
</Area>
<Area>
<Name>岩手県岩手町</Name>
<Code>0330300</Code>
</Area>
<Area>
<Name>岩手県岩泉町</Name>
<Code>0348300</Code>
</Area>
</Areas>
</Item>
<Item>
<Kind>
<Name>小さな噴石の落下</Name>
<Code>75</Code>
<Property>
<Size type="小さな噴石の大きさ" unit="cm">1</Size>
<jmx_eb:Polygon type="位置（度）">+39.8788+140.9800/+39.8750+141.0000/+39.8607+141.0200/+39.8600+141.0211/+39.8546+141.0200/+39.8400+141.0193/+39.8259+141.0000/+39.8213+140.9800/+39.8400+140.9613/+39.8600+140.9612/+39.8788+140.9800/</jmx_eb:Polygon>
<jmx_eb:PlumeDirection type="小さな噴石の落下方向" unit="漢字" description="東">東</jmx_eb:PlumeDirection>
<Distance type="小さな噴石の到達距離" unit="km">4</Distance>
</Property>
</Kind>
<Areas codeType="気象・地震・火山情報／市町村等">
<Area>
<Name>岩手県八幡平市</Name>
<Code>0321400</Code>
</Area>
<Area>
<Name>岩手県滝沢市</Name>
<Code>0321600</Code>
</Area>
<Area>
<Name>岩手県雫石町</Name>
<Code>0330100</Code>
</Area>
</Areas>
</Item>
</AshInfo>
<AshInfo type="予報　１５時間後">
<StartTime>2025-12-29T00:00:00+09:00</StartTime>
<EndTime>2025-12-29T03:00:00+09:00</EndTime>
<Item>
<Kind>
<Name>降灰</Name>
<Code>70</Code>
<Property>
<jmx_eb:Polygon type="位置（度）">+40.1210+141.2400/+40.1294+141.2600/+40.1331+141.2800/+40.1336+141.3000/+40.1338+141.3200/+40.1297+141.3400/+40.1252+141.3600/+40.1257+141.3800/+40.1263+141.4000/+40.1257+141.4200/+40.1242+141.4400/+40.1200+141.4462/+40.1000+141.4595/+40.0992+141.4600/+40.0800+141.4778/+40.0780+141.4800/+40.0707+141.5000/+40.0600+141.5147/+40.0400+141.5192/+40.0200+141.5009/+40.0195+141.5000/+40.0200+141.4958/+40.0221+141.4800/+40.0253+141.4600/+40.0295+141.4400/+40.0200+141.4276/+40.0132+141.4200/+40.0000+141.4078/+39.9964+141.4000/+39.9900+141.3800/+39.9800+141.3608/+39.9798+141.3600/+39.9772+141.3400/+39.9769+141.3200/+39.9742+141.3000/+39.9688+141.2800/+39.9665+141.2600/+39.9661+141.2400/+39.9600+141.2280/+39.9562+141.2200/+39.9506+141.2000/+39.9452+141.1800/+39.9400+141.1627/+39.9386+141.1600/+39.9236+141.1400/+39.9200+141.1359/+39.9071+141.1200/+39.9000+141.1031/+39.8972+141.1000/+39.8800+141.0814/+39.8786+141.0800/+39.8610+141.0600/+39.8600+141.0567/+39.8443+141.0400/+39.8402+141.0200/+39.8400+141.0194/+39.8208+141.0000/+39.8202+140.9800/+39.8229+140.9600/+39.8400+140.9429/+39.8600+140.9410/+39.8791+140.9600/+39.8800+140.9601/+39.9000+140.9639/+39.9161+140.9800/+39.9200+140.9822/+39.9400+140.9985/+39.9416+141.0000/+39.9600+141.0039/+39.9800+141.0144/+39.9894+141.0200/+40.0000+141.0227/+40.0200+141.0295/+40.0355+141.0400/+40.0400+141.0438/+40.0582+141.0600/+40.0600+141.0638/+40.0778+141.0800/+40.0800+141.0814/+40.0934+141.1000/+40.0989+141.1200/+40.1000+141.1359/+40.1005+141.1400/+40.1087+141.1600/+40.1133+141.1800/+40.1160+141.2000/+40.1175+141.2200/+40.1200+141.2358/+40.1210+141.2400/</jmx_eb:Polygon>
<jmx_eb:PlumeDirection type="降灰の方向" unit="漢字" description="北東">北東</jmx_eb:PlumeDirection>
<Distance type="降灰の到達距離" unit="km">50</Distance>
</Property>
</Kind>
<Areas codeType="気象・地震・火山情報／市町村等">
<Area>
<Name>岩手県二戸市</Name>
<Code>0321300</Code>
</Area>
<Area>
<Name>岩手県八幡平市</Name>
<Code>0321400</Code>
</Area>
<Area>
<Name>岩手県滝沢市</Name>
<Code>0321600</Code>
</Area>
<Area>
<Name>岩手県雫石町</Name>
<Code>0330100</Code>
</Area>
<Area>
<Name>岩手県葛巻町</Name>
<Code>0330200</Code>
</Area>
<Area>
<Name>岩手県岩手町</Name>
<Code>0330300</Code>
</Area>
<Area>
<Name>岩手県九戸村</Name>
<Code>0350600</Code>
</Area>
<Area>
<Name>岩手県一戸町</Name>
<Code>0352400</Code>
</Area>
</Areas>
</Item>
<Item>
<Kind>
<Name>小さな噴石の落下</Name>
<Code>75</Code>
<Property>
<Size type="小さな噴石の大きさ" unit="cm">1</Size>
<jmx_eb:Polygon type="位置（度）">+39.8793+140.9800/+39.8767+141.0000/+39.8600+141.0186/+39.8400+141.0113/+39.8287+141.0000/+39.8400+140.9887/+39.8412+140.9800/+39.8600+140.9612/+39.8793+140.9800/</jmx_eb:Polygon>
<jmx_eb:PlumeDirection type="小さな噴石の落下方向" unit="漢字" description="東">東</jmx_eb:PlumeDirection>
<Distance type="小さな噴石の到達距離" unit="km">3</Distance>
</Property>
</Kind>
<Areas codeType="気象・地震・火山情報／市町村等">
<Area>
<Name>岩手県八幡平市</Name>
<Code>0321400</Code>
</Area>
<Area>
<Name>岩手県滝沢市</Name>
<Code>0321600</Code>
</Area>
<Area>
<Name>岩手県雫石町</Name>
<Code>0330100</Code>
</Area>
</Areas>
</Item>
</AshInfo>
<AshInfo type="予報　１８時間後">
<StartTime>2025-12-29T03:00:00+09:00</StartTime>
<EndTime>2025-12-29T06:00:00+09:00</EndTime>
<Item>
<Kind>
<Name>降灰</Name>
<Code>70</Code>
<Property>
<jmx_eb:Polygon type="位置（度）">+40.2904+141.2000/+40.2883+141.2200/+40.2845+141.2400/+40.2800+141.2550/+40.2781+141.2600/+40.2722+141.2800/+40.2664+141.3000/+40.2600+141.3061/+40.2424+141.3000/+40.2400+141.2977/+40.2324+141.2800/+40.2248+141.2600/+40.2231+141.2400/+40.2200+141.2386/+40.2000+141.2294/+40.1800+141.2272/+40.1600+141.2251/+40.1545+141.2200/+40.1400+141.2084/+40.1200+141.2058/+40.1063+141.2000/+40.1000+141.1982/+40.0800+141.1889/+40.0689+141.1800/+40.0600+141.1728/+40.0484+141.1600/+40.0400+141.1525/+40.0315+141.1400/+40.0200+141.1273/+40.0125+141.1200/+40.0000+141.1120/+39.9859+141.1000/+39.9800+141.0981/+39.9600+141.0874/+39.9520+141.0800/+39.9400+141.0760/+39.9217+141.0600/+39.9200+141.0596/+39.9000+141.0507/+39.8890+141.0400/+39.8800+141.0387/+39.8603+141.0200/+39.8600+141.0200/+39.8400+141.0123/+39.8277+141.0000/+39.8204+140.9800/+39.8222+140.9600/+39.8400+140.9422/+39.8600+140.9404/+39.8800+140.9463/+39.8937+140.9600/+39.9000+140.9602/+39.9200+140.9650/+39.9356+140.9800/+39.9400+140.9805/+39.9600+140.9826/+39.9800+140.9876/+40.0000+140.9976/+40.0066+141.0000/+40.0200+141.0007/+40.0400+141.0020/+40.0600+141.0033/+40.0800+141.0046/+40.1000+141.0092/+40.1200+141.0120/+40.1351+141.0200/+40.1400+141.0217/+40.1600+141.0308/+40.1734+141.0400/+40.1800+141.0466/+40.1912+141.0600/+40.2000+141.0733/+40.2068+141.0800/+40.2200+141.0953/+40.2231+141.1000/+40.2347+141.1200/+40.2400+141.1315/+40.2505+141.1400/+40.2600+141.1482/+40.2708+141.1600/+40.2788+141.1800/+40.2800+141.1827/+40.2904+141.2000/</jmx_eb:Polygon>
<jmx_eb:PlumeDirection type="降灰の方向" unit="漢字" description="北東">北東</jmx_eb:PlumeDirection>
<Distance type="降灰の到達距離" unit="km">50</Distance>
</Property>
</Kind>
<Areas codeType="気象・地震・火山情報／市町村等">
<Area>
<Name>岩手県二戸市</Name>
<Code>0321300</Code>
</Area>
<Area>
<Name>岩手県八幡平市</Name>
<Code>0321400</Code>
</Area>
<Area>
<Name>岩手県滝沢市</Name>
<Code>0321600</Code>
</Area>
<Area>
<Name>岩手県雫石町</Name>
<Code>0330100</Code>
</Area>
<Area>
<Name>岩手県岩手町</Name>
<Code>0330300</Code>
</Area>
<Area>
<Name>岩手県一戸町</Name>
<Code>0352400</Code>
</Area>
</Areas>
</Item>
<Item>
<Kind>
<Name>小さな噴石の落下</Name>
<Code>75</Code>
<Property>
<Size type="小さな噴石の大きさ" unit="cm">1</Size>
<jmx_eb:Polygon type="位置（度）">+39.8816+140.9800/+39.8843+141.0000/+39.8800+141.0039/+39.8600+141.0123/+39.8477+141.0000/+39.8412+140.9800/+39.8600+140.9612/+39.8800+140.9786/+39.8816+140.9800/</jmx_eb:Polygon>
<jmx_eb:PlumeDirection type="小さな噴石の落下方向" unit="漢字" description="北東">北東</jmx_eb:PlumeDirection>
<Distance type="小さな噴石の到達距離" unit="km">4</Distance>
</Property>
</Kind>
<Areas codeType="気象・地震・火山情報／市町村等">
<Area>
<Name>岩手県八幡平市</Name>
<Code>0321400</Code>
</Area>
<Area>
<Name>岩手県滝沢市</Name>
<Code>0321600</Code>
</Area>
</Areas>
</Item>
</AshInfo>
</AshInfos>
<VolcanoInfoContent>
<VolcanoHeadline>　現在、岩手山は噴火警戒レベル２（火口周辺規制）です。岩手山で噴火が発生した場合には、２８日２１時から２４時までは火口から東方向に降灰が予想されます。</VolcanoHeadline>
<VolcanoActivity>　２８日１２時から２９日６時までに噴火が発生した場合には、以下の方向・距離に降灰及び小さな噴石の落下が予想されます。
　
　時刻　　　　　　　　　　　　火口からの方向　降灰の距離　小さな噴石の距離
　２８日１２時から１５時まで　東　　　　　　　７０ｋｍ　　４ｋｍ　　　　　
　２８日１５時から１８時まで　東　　　　　　　７０ｋｍ　　４ｋｍ　　　　　
　２８日１８時から２１時まで　東　　　　　　　６０ｋｍ　　４ｋｍ　　　　　
　２８日２１時から２４時まで　東　　　　　　　６０ｋｍ　　４ｋｍ　　　　　
　２９日００時から０３時まで　北東　　　　　　５０ｋｍ　　３ｋｍ　　　　　
　２９日０３時から０６時まで　北東　　　　　　５０ｋｍ　　４ｋｍ　　　　　

　
　期間中に噴火が発生した場合には、以下の市町村に降灰が予想されます。
　岩手県　：盛岡市、宮古市、八幡平市、滝沢市、雫石町、岩泉町、岩手町、葛巻町、二戸市、九戸村、
　　　　　一戸町
　</VolcanoActivity>
<VolcanoPrevention>　噴煙が火口縁上１０００ｍまで上がった場合の火山灰及び小さな噴石の落下範囲を示しています。
　噴火発生時、小さな噴石の落下が予想される範囲内では、屋内や頑丈な屋根の下などに移動してください。
　</VolcanoPrevention>
</VolcanoInfoContent>
</Body>
</Report>
